pandas_aiohttp/__init__.py
pandas_aiohttp-0.1.0.dist-info/METADATA
pandas_aiohttp-0.1.0.dist-info/WHEEL
pandas_aiohttp-0.1.0.dist-info/licenses/LICENSE.txt
pandas_aiohttp-0.1.0.dist-info/RECORD
