Metadata-Version: 2.1
Name: pandas-aiohttp
Version: 0.1.0
Summary: Adds `Series.aiohttp.get_text()` and `Series.aiohttp.get_json()` to pandas Series objects.
Project-URL: Documentation, https://github.com/thehappycheese/pandas-aiohttp#readme
Project-URL: Issues, https://github.com/thehappycheese/pandas-aiohttp/issues
Project-URL: Source, https://github.com/thehappycheese/pandas-aiohttp
Author: thehappycheese
License-Expression: MIT
License-File: LICENSE.txt
Keywords: aiohttp,pandas,urls
Requires-Python: >=3.10
Requires-Dist: aiohttp
Requires-Dist: pandas
